adapter/__init__.py
adapter/device.py
awox_mesh_light_webthing-0.0.8.dist-info/LICENSE
awox_mesh_light_webthing-0.0.8.dist-info/METADATA
awox_mesh_light_webthing-0.0.8.dist-info/WHEEL
awox_mesh_light_webthing-0.0.8.dist-info/top_level.txt
awox_mesh_light_webthing-0.0.8.dist-info/RECORD
