Metadata-Version: 2.1
Name: awox-mesh-light-webthing
Version: 0.0.8
Summary: Awox Mesh Light WebThing
Home-page: https://github.com/rzr/awox-mesh-light-webthing/
Author: Philippe Coval
Author-email: rzr@users.sf.net
License: MIT
Project-URL: Source, https://github.com/rzr/awox-mesh-light-webthing/
Project-URL: Tracker, https://github.com/rzr/awox-mesh-light-webthing//issues
Keywords: Awox mesh light bluetooth web thing webthing
Platform: UNKNOWN
Classifier: Intended Audience :: Developers
Classifier: License :: OSI Approved :: MIT License
Classifier: Programming Language :: Python :: 3.7
Requires-Python: >=3.7se, <4
